pentagon_functions/__init__.py
pentagon_functions/pentagon_functions.py
pentagon_functions/pentagon_monomial.py
pentagon_functions/version.py
pentagon_functions-0.0.6.dist-info/METADATA
pentagon_functions-0.0.6.dist-info/WHEEL
pentagon_functions-0.0.6.dist-info/top_level.txt
pentagon_functions-0.0.6.dist-info/RECORD
