Metadata-Version: 2.1
Name: pentagon-functions
Version: 0.0.6
Summary: A Python interface to PentagonFunctions-cpp
Home-page: https://github.com/GDeLaurentis/py-pentagon-functions
Author: Giuseppe De Laurentis and the Pentagon Functions authors
License: UNKNOWN
Download-URL: https://github.com/GDeLaurentis/py-pentagon-functions/archive/v0.0.6.tar.gz
Project-URL: Issues, https://github.com/GDeLaurentis/py-pentagon-functions/issues
Keywords: Scattering Amplitudes,Feynman Integrals,Pentagon Functions
Platform: UNKNOWN
Classifier: Development Status :: 4 - Beta
Classifier: Intended Audience :: Science/Research
Classifier: Topic :: Scientific/Engineering :: Physics
Classifier: Programming Language :: Python :: 3.9
Classifier: Programming Language :: Python :: 3.10
Classifier: Programming Language :: Python :: 3.11
Classifier: Programming Language :: Python :: 3.12
Requires-Dist: lips
Requires-Dist: mpmath
Requires-Dist: numpy
Requires-Dist: whichcraft
Provides-Extra: with-cpp
Requires-Dist: meson ; extra == 'with-cpp'
Requires-Dist: ninja ; extra == 'with-cpp'
